{
  "users": [
    {
      "id": 1,
      "email": "GlenysHunter@gmail.com",
      "title": "Miss",
      "firstName": "Glenys",
      "lastName": "Hunter",
      "doB": "2005-02-27T00:00:00",
      "phoneNum": "128330260",
      "thumbnailImgURL": "https://picsum.photos/200"
    },
    {
      "id": 2,
      "email": "GeorgiaRetter@gmail.com",
      "title": "Ms",
      "firstName": "Georgia",
      "lastName": "Retter",
      "doB": "2004-03-17T00:00:00",
      "phoneNum": "615350585",
      "thumbnailImgURL": "https://picsum.photos/200"
    },
    {
      "id": 3,
      "email": "HarrySchgo@gmail.com",
      "title": "Ms",
      "firstName": "Harry",
      "lastName": "Schgo",
      "doB": "2020-01-24T00:00:00",
      "phoneNum": "717020022",
      "thumbnailImgURL": "https://picsum.photos/200"
    },
    {
      "id": 4,
      "email": "KadeCalder@gmail.com",
      "title": "Mrs",
      "firstName": "Kade",
      "lastName": "Calder",
      "doB": "2012-09-30T00:00:00",
      "phoneNum": "261157749",
      "thumbnailImgURL": "https://picsum.photos/200"
    },
    {
      "id": 5,
      "email": "GeorgiaMcDonald@gmail.com",
      "title": "Ms",
      "firstName": "Georgia",
      "lastName": "McDonald",
      "doB": "2010-04-22T00:00:00",
      "phoneNum": "408024411",
      "thumbnailImgURL": "https://picsum.photos/200"
    },
    {
      "id": 6,
      "email": "SamCalder@gmail.com",
      "title": "Mr",
      "firstName": "Sam",
      "lastName": "Calder",
      "doB": "2008-12-01T00:00:00",
      "phoneNum": "477407173",
      "thumbnailImgURL": "https://picsum.photos/200"
    },
    {
      "id": 7,
      "email": "LilyCalder@gmail.com",
      "title": "Mr",
      "firstName": "Lily",
      "lastName": "Calder",
      "doB": "2018-08-24T00:00:00",
      "phoneNum": "268473242",
      "thumbnailImgURL": "https://picsum.photos/200"
    },
    {
      "id": 8,
      "email": "BlairMcDonald@gmail.com",
      "title": "Ms",
      "firstName": "Blair",
      "lastName": "McDonald",
      "doB": "1997-03-25T00:00:00",
      "phoneNum": "871268578",
      "thumbnailImgURL": "https://picsum.photos/200"
    },
    {
      "id": 9,
      "email": "KadeLee@gmail.com",
      "title": "Ms",
      "firstName": "Kade",
      "lastName": "Lee",
      "doB": "2001-06-25T00:00:00",
      "phoneNum": "497139524",
      "thumbnailImgURL": "https://picsum.photos/200"
    },
    {
      "id": 10,
      "email": "SarahBlack@gmail.com",
      "title": "Miss",
      "firstName": "Sarah",
      "lastName": "Black",
      "doB": "2020-04-18T00:00:00",
      "phoneNum": "398177204",
      "thumbnailImgURL": "https://picsum.photos/200"
    },
    {
      "id": 11,
      "email": "SarahFlynn@gmail.com",
      "title": "Dr",
      "firstName": "Sarah",
      "lastName": "Flynn",
      "doB": "1995-03-14T00:00:00",
      "phoneNum": "508564699",
      "thumbnailImgURL": "https://picsum.photos/200"
    },
    {
      "id": 12,
      "email": "PollyPoland@gmail.com",
      "title": "Ms",
      "firstName": "Polly",
      "lastName": "Poland",
      "doB": "2020-10-31T00:00:00",
      "phoneNum": "280663367",
      "thumbnailImgURL": "https://picsum.photos/200"
    },
    {
      "id": 13,
      "email": "JuneNorris@gmail.com",
      "title": "Miss",
      "firstName": "June",
      "lastName": "Norris",
      "doB": "1997-07-05T00:00:00",
      "phoneNum": "662910100",
      "thumbnailImgURL": "https://picsum.photos/200"
    },
    {
      "id": 14,
      "email": "MaxErickson@gmail.com",
      "title": "Mrs",
      "firstName": "Max",
      "lastName": "Erickson",
      "doB": "2010-10-25T00:00:00",
      "phoneNum": "696198002",
      "thumbnailImgURL": "https://picsum.photos/200"
    },
    {
      "id": 15,
      "email": "KadeHunter@gmail.com",
      "title": "Dr",
      "firstName": "Kade",
      "lastName": "Hunter",
      "doB": "1999-12-23T00:00:00",
      "phoneNum": "655856132",
      "thumbnailImgURL": "https://picsum.photos/200"
    },
    {
      "id": 16,
      "email": "BlairLee@gmail.com",
      "title": "Mrs",
      "firstName": "Blair",
      "lastName": "Lee",
      "doB": "2008-04-30T00:00:00",
      "phoneNum": "169216233",
      "thumbnailImgURL": "https://picsum.photos/200"
    },
    {
      "id": 17,
      "email": "KadeBlack@gmail.com",
      "title": "Ms",
      "firstName": "Kade",
      "lastName": "Black",
      "doB": "2005-06-08T00:00:00",
      "phoneNum": "632697736",
      "thumbnailImgURL": "https://picsum.photos/200"
    },
    {
      "id": 18,
      "email": "GeorgiaFlynn@gmail.com",
      "title": "Mr",
      "firstName": "Georgia",
      "lastName": "Flynn",
      "doB": "1999-04-21T00:00:00",
      "phoneNum": "673223137",
      "thumbnailImgURL": "https://picsum.photos/200"
    },
    {
      "id": 19,
      "email": "JuneNorris@gmail.com",
      "title": "Mrs",
      "firstName": "June",
      "lastName": "Norris",
      "doB": "2006-06-15T00:00:00",
      "phoneNum": "177395943",
      "thumbnailImgURL": "https://picsum.photos/200"
    },
    {
      "id": 20,
      "email": "BlairLee@gmail.com",
      "title": "Dr",
      "firstName": "Blair",
      "lastName": "Lee",
      "doB": "2003-06-26T00:00:00",
      "phoneNum": "920490064",
      "thumbnailImgURL": "https://picsum.photos/200"
    },
    {
      "id": 21,
      "email": "SamLee@gmail.com",
      "title": "Mr",
      "firstName": "Sam",
      "lastName": "Lee",
      "doB": "2010-08-03T00:00:00",
      "phoneNum": "312600771",
      "thumbnailImgURL": "https://picsum.photos/200"
    },
    {
      "id": 22,
      "email": "LilyCalder@gmail.com",
      "title": "Ms",
      "firstName": "Lily",
      "lastName": "Calder",
      "doB": "2002-03-24T00:00:00",
      "phoneNum": "366640703",
      "thumbnailImgURL": "https://picsum.photos/200"
    },
    {
      "id": 23,
      "email": "MaxNorris@gmail.com",
      "title": "Miss",
      "firstName": "Max",
      "lastName": "Norris",
      "doB": "2014-02-14T00:00:00",
      "phoneNum": "737772880",
      "thumbnailImgURL": "https://picsum.photos/200"
    },
    {
      "id": 24,
      "email": "PandoraMcDonald@gmail.com",
      "title": "Miss",
      "firstName": "Pandora",
      "lastName": "McDonald",
      "doB": "2008-08-24T00:00:00",
      "phoneNum": "304343805",
      "thumbnailImgURL": "https://picsum.photos/200"
    },
    {
      "id": 25,
      "email": "JuneErickson@gmail.com",
      "title": "Ms",
      "firstName": "June",
      "lastName": "Erickson",
      "doB": "2005-05-31T00:00:00",
      "phoneNum": "577413178",
      "thumbnailImgURL": "https://picsum.photos/200"
    },
    {
      "id": 26,
      "email": "LilyMusk@gmail.com",
      "title": "Dr",
      "firstName": "Lily",
      "lastName": "Musk",
      "doB": "2003-07-21T00:00:00",
      "phoneNum": "388420624",
      "thumbnailImgURL": "https://picsum.photos/200"
    },
    {
      "id": 27,
      "email": "BlairGray@gmail.com",
      "title": "Dr",
      "firstName": "Blair",
      "lastName": "Gray",
      "doB": "2006-09-09T00:00:00",
      "phoneNum": "213401206",
      "thumbnailImgURL": "https://picsum.photos/200"
    },
    {
      "id": 28,
      "email": "BlairErickson@gmail.com",
      "title": "Dr",
      "firstName": "Blair",
      "lastName": "Erickson",
      "doB": "2020-04-15T00:00:00",
      "phoneNum": "991473120",
      "thumbnailImgURL": "https://picsum.photos/200"
    },
    {
      "id": 29,
      "email": "MaxJames@gmail.com",
      "title": "Mr",
      "firstName": "Max",
      "lastName": "James",
      "doB": "1996-07-22T00:00:00",
      "phoneNum": "624982889",
      "thumbnailImgURL": "https://picsum.photos/200"
    },
    {
      "id": 30,
      "email": "SamErickson@gmail.com",
      "title": "Mr",
      "firstName": "Sam",
      "lastName": "Erickson",
      "doB": "2015-05-27T00:00:00",
      "phoneNum": "393099907",
      "thumbnailImgURL": "https://picsum.photos/200"
    },
    {
      "id": 31,
      "email": "PollyLee@gmail.com",
      "title": "Dr",
      "firstName": "Polly",
      "lastName": "Lee",
      "doB": "1995-08-07T00:00:00",
      "phoneNum": "385484194",
      "thumbnailImgURL": "https://picsum.photos/200"
    },
    {
      "id": 32,
      "email": "BlairCalder@gmail.com",
      "title": "Mr",
      "firstName": "Blair",
      "lastName": "Calder",
      "doB": "2007-07-18T00:00:00",
      "phoneNum": "878955188",
      "thumbnailImgURL": "https://picsum.photos/200"
    },
    {
      "id": 33,
      "email": "SamFlynn@gmail.com",
      "title": "Mr",
      "firstName": "Sam",
      "lastName": "Flynn",
      "doB": "2011-11-19T00:00:00",
      "phoneNum": "627448165",
      "thumbnailImgURL": "https://picsum.photos/200"
    },
    {
      "id": 34,
      "email": "MarySchgo@gmail.com",
      "title": "Ms",
      "firstName": "Mary",
      "lastName": "Schgo",
      "doB": "1999-12-20T00:00:00",
      "phoneNum": "196099381",
      "thumbnailImgURL": "https://picsum.photos/200"
    },
    {
      "id": 35,
      "email": "SarahGray@gmail.com",
      "title": "Miss",
      "firstName": "Sarah",
      "lastName": "Gray",
      "doB": "2005-06-12T00:00:00",
      "phoneNum": "438140997",
      "thumbnailImgURL": "https://picsum.photos/200"
    },
    {
      "id": 36,
      "email": "GlenysLee@gmail.com",
      "title": "Mr",
      "firstName": "Glenys",
      "lastName": "Lee",
      "doB": "1997-04-13T00:00:00",
      "phoneNum": "295248288",
      "thumbnailImgURL": "https://picsum.photos/200"
    },
    {
      "id": 37,
      "email": "PandoraMusk@gmail.com",
      "title": "Mr",
      "firstName": "Pandora",
      "lastName": "Musk",
      "doB": "1996-12-29T00:00:00",
      "phoneNum": "617430268",
      "thumbnailImgURL": "https://picsum.photos/200"
    },
    {
      "id": 38,
      "email": "TerranceJames@gmail.com",
      "title": "Mrs",
      "firstName": "Terrance",
      "lastName": "James",
      "doB": "2005-03-27T00:00:00",
      "phoneNum": "618966546",
      "thumbnailImgURL": "https://picsum.photos/200"
    },
    {
      "id": 39,
      "email": "PandoraFlynn@gmail.com",
      "title": "Miss",
      "firstName": "Pandora",
      "lastName": "Flynn",
      "doB": "2005-02-03T00:00:00",
      "phoneNum": "238858661",
      "thumbnailImgURL": "https://picsum.photos/200"
    },
    {
      "id": 40,
      "email": "JuneBlack@gmail.com",
      "title": "Mr",
      "firstName": "June",
      "lastName": "Black",
      "doB": "2001-07-28T00:00:00",
      "phoneNum": "674589623",
      "thumbnailImgURL": "https://picsum.photos/200"
    },
    {
      "id": 41,
      "email": "BlairNorris@gmail.com",
      "title": "Mrs",
      "firstName": "Blair",
      "lastName": "Norris",
      "doB": "2020-07-09T00:00:00",
      "phoneNum": "869913686",
      "thumbnailImgURL": "https://picsum.photos/200"
    },
    {
      "id": 42,
      "email": "SarahJames@gmail.com",
      "title": "Mrs",
      "firstName": "Sarah",
      "lastName": "James",
      "doB": "2018-08-05T00:00:00",
      "phoneNum": "463467575",
      "thumbnailImgURL": "https://picsum.photos/200"
    },
    {
      "id": 43,
      "email": "LilyFlynn@gmail.com",
      "title": "Ms",
      "firstName": "Lily",
      "lastName": "Flynn",
      "doB": "1997-04-20T00:00:00",
      "phoneNum": "849077395",
      "thumbnailImgURL": "https://picsum.photos/200"
    },
    {
      "id": 44,
      "email": "JackRetter@gmail.com",
      "title": "Dr",
      "firstName": "Jack",
      "lastName": "Retter",
      "doB": "2014-10-10T00:00:00",
      "phoneNum": "996675984",
      "thumbnailImgURL": "https://picsum.photos/200"
    },
    {
      "id": 45,
      "email": "PandoraFlynn@gmail.com",
      "title": "Ms",
      "firstName": "Pandora",
      "lastName": "Flynn",
      "doB": "2006-12-31T00:00:00",
      "phoneNum": "520235212",
      "thumbnailImgURL": "https://picsum.photos/200"
    },
    {
      "id": 46,
      "email": "PollyPoland@gmail.com",
      "title": "Dr",
      "firstName": "Polly",
      "lastName": "Poland",
      "doB": "2005-10-30T00:00:00",
      "phoneNum": "844635185",
      "thumbnailImgURL": "https://picsum.photos/200"
    },
    {
      "id": 47,
      "email": "KadeFlynn@gmail.com",
      "title": "Miss",
      "firstName": "Kade",
      "lastName": "Flynn",
      "doB": "1996-10-01T00:00:00",
      "phoneNum": "745259367",
      "thumbnailImgURL": "https://picsum.photos/200"
    },
    {
      "id": 48,
      "email": "SamLee@gmail.com",
      "title": "Ms",
      "firstName": "Sam",
      "lastName": "Lee",
      "doB": "1999-08-08T00:00:00",
      "phoneNum": "918712574",
      "thumbnailImgURL": "https://picsum.photos/200"
    },
    {
      "id": 49,
      "email": "KadeMusk@gmail.com",
      "title": "Ms",
      "firstName": "Kade",
      "lastName": "Musk",
      "doB": "2011-05-02T00:00:00",
      "phoneNum": "811959807",
      "thumbnailImgURL": "https://picsum.photos/200"
    },
    {
      "id": 50,
      "email": "GeorgiaNorris@gmail.com",
      "title": "Dr",
      "firstName": "Georgia",
      "lastName": "Norris",
      "doB": "1998-08-02T00:00:00",
      "phoneNum": "884074809",
      "thumbnailImgURL": "https://picsum.photos/200"
    }
  ]
}